{"nodes": [{"id": "users_satnam_workstation_smriti_src_tauri_src_mcp_rs", "label": "mcp.rs", "file_type": "code", "source_file": "src-tauri/src/mcp.rs", "source_location": "L1"}, {"id": "src_mcp_mcptool", "label": "McpTool", "file_type": "code", "source_file": "src-tauri/src/mcp.rs", "source_location": "L10"}, {"id": "string", "label": "String", "file_type": "code", "source_file": "src-tauri/src/mcp.rs", "source_location": "L11"}, {"id": "option", "label": "Option", "file_type": "code", "source_file": "src-tauri/src/mcp.rs", "source_location": "L12"}, {"id": "src_mcp_ingest_sse", "label": "ingest_sse()", "file_type": "code", "source_file": "src-tauri/src/mcp.rs", "source_location": "L15"}, {"id": "vec", "label": "Vec", "file_type": "code", "source_file": "src-tauri/src/mcp.rs", "source_location": "L15"}, {"id": "value", "label": "Value", "file_type": "code", "source_file": "src-tauri/src/mcp.rs", "source_location": "L15"}, {"id": "src_mcp_session_id", "label": "session_id()", "file_type": "code", "source_file": "src-tauri/src/mcp.rs", "source_location": "L34"}, {"id": "src_mcp_post_json", "label": "post_json()", "file_type": "code", "source_file": "src-tauri/src/mcp.rs", "source_location": "L43"}, {"id": "client", "label": "Client", "file_type": "code", "source_file": "src-tauri/src/mcp.rs", "source_location": "L43"}, {"id": "result", "label": "Result", "file_type": "code", "source_file": "src-tauri/src/mcp.rs", "source_location": "L43"}, {"id": "src_mcp_wait_for_id", "label": "wait_for_id()", "file_type": "code", "source_file": "src-tauri/src/mcp.rs", "source_location": "L54"}, {"id": "arc", "label": "Arc", "file_type": "code", "source_file": "src-tauri/src/mcp.rs", "source_location": "L54"}, {"id": "mutex", "label": "Mutex", "file_type": "code", "source_file": "src-tauri/src/mcp.rs", "source_location": "L54"}, {"id": "duration", "label": "Duration", "file_type": "code", "source_file": "src-tauri/src/mcp.rs", "source_location": "L54"}, {"id": "src_mcp_run_rpc", "label": "run_rpc()", "file_type": "code", "source_file": "src-tauri/src/mcp.rs", "source_location": "L74"}, {"id": "src_mcp_list_tools", "label": "list_tools()", "file_type": "code", "source_file": "src-tauri/src/mcp.rs", "source_location": "L182"}, {"id": "src_mcp_call_tool", "label": "call_tool()", "file_type": "code", "source_file": "src-tauri/src/mcp.rs", "source_location": "L206"}, {"id": "src_mcp_clean_tool_error", "label": "clean_tool_error()", "file_type": "code", "source_file": "src-tauri/src/mcp.rs", "source_location": "L236"}, {"id": "src_mcp_format_tool_text", "label": "format_tool_text()", "file_type": "code", "source_file": "src-tauri/src/mcp.rs", "source_location": "L250"}], "edges": [{"source": "users_satnam_workstation_smriti_src_tauri_src_mcp_rs", "target": "streamext", "relation": "imports_from", "confidence": "EXTRACTED", "source_file": "src-tauri/src/mcp.rs", "source_location": "L1", "weight": 1.0, "context": "import"}, {"source": "users_satnam_workstation_smriti_src_tauri_src_mcp_rs", "target": "client", "relation": "imports_from", "confidence": "EXTRACTED", "source_file": "src-tauri/src/mcp.rs", "source_location": "L2", "weight": 1.0, "context": "import"}, {"source": "users_satnam_workstation_smriti_src_tauri_src_mcp_rs", "target": "serde", "relation": "imports_from", "confidence": "EXTRACTED", "source_file": "src-tauri/src/mcp.rs", "source_location": "L3", "weight": 1.0, "context": "import"}, {"source": "users_satnam_workstation_smriti_src_tauri_src_mcp_rs", "target": "serde_json", "relation": "imports_from", "confidence": "EXTRACTED", "source_file": "src-tauri/src/mcp.rs", "source_location": "L4", "weight": 1.0, "context": "import"}, {"source": "users_satnam_workstation_smriti_src_tauri_src_mcp_rs", "target": "arc", "relation": "imports_from", "confidence": "EXTRACTED", "source_file": "src-tauri/src/mcp.rs", "source_location": "L5", "weight": 1.0, "context": "import"}, {"source": "users_satnam_workstation_smriti_src_tauri_src_mcp_rs", "target": "time", "relation": "imports_from", "confidence": "EXTRACTED", "source_file": "src-tauri/src/mcp.rs", "source_location": "L6", "weight": 1.0, "context": "import"}, {"source": "users_satnam_workstation_smriti_src_tauri_src_mcp_rs", "target": "mutex", "relation": "imports_from", "confidence": "EXTRACTED", "source_file": "src-tauri/src/mcp.rs", "source_location": "L7", "weight": 1.0, "context": "import"}, {"source": "users_satnam_workstation_smriti_src_tauri_src_mcp_rs", "target": "src_mcp_mcptool", "relation": "contains", "confidence": "EXTRACTED", "source_file": "src-tauri/src/mcp.rs", "source_location": "L10", "weight": 1.0}, {"source": "src_mcp_mcptool", "target": "string", "relation": "references", "confidence": "EXTRACTED", "source_file": "src-tauri/src/mcp.rs", "source_location": "L11", "weight": 1.0, "context": "field"}, {"source": "src_mcp_mcptool", "target": "option", "relation": "references", "confidence": "EXTRACTED", "source_file": "src-tauri/src/mcp.rs", "source_location": "L12", "weight": 1.0, "context": "field"}, {"source": "src_mcp_mcptool", "target": "string", "relation": "references", "confidence": "EXTRACTED", "source_file": "src-tauri/src/mcp.rs", "source_location": "L12", "weight": 1.0, "context": "generic_arg"}, {"source": "users_satnam_workstation_smriti_src_tauri_src_mcp_rs", "target": "src_mcp_ingest_sse", "relation": "contains", "confidence": "EXTRACTED", "source_file": "src-tauri/src/mcp.rs", "source_location": "L15", "weight": 1.0}, {"source": "src_mcp_ingest_sse", "target": "vec", "relation": "references", "confidence": "EXTRACTED", "source_file": "src-tauri/src/mcp.rs", "source_location": "L15", "weight": 1.0, "context": "parameter_type"}, {"source": "src_mcp_ingest_sse", "target": "value", "relation": "references", "confidence": "EXTRACTED", "source_file": "src-tauri/src/mcp.rs", "source_location": "L15", "weight": 1.0, "context": "generic_arg"}, {"source": "users_satnam_workstation_smriti_src_tauri_src_mcp_rs", "target": "src_mcp_session_id", "relation": "contains", "confidence": "EXTRACTED", "source_file": "src-tauri/src/mcp.rs", "source_location": "L34", "weight": 1.0}, {"source": "src_mcp_session_id", "target": "option", "relation": "references", "confidence": "EXTRACTED", "source_file": "src-tauri/src/mcp.rs", "source_location": "L34", "weight": 1.0, "context": "return_type"}, {"source": "src_mcp_session_id", "target": "string", "relation": "references", "confidence": "EXTRACTED", "source_file": "src-tauri/src/mcp.rs", "source_location": "L34", "weight": 1.0, "context": "generic_arg"}, {"source": "users_satnam_workstation_smriti_src_tauri_src_mcp_rs", "target": "src_mcp_post_json", "relation": "contains", "confidence": "EXTRACTED", "source_file": "src-tauri/src/mcp.rs", "source_location": "L43", "weight": 1.0}, {"source": "src_mcp_post_json", "target": "client", "relation": "references", "confidence": "EXTRACTED", "source_file": "src-tauri/src/mcp.rs", "source_location": "L43", "weight": 1.0, "context": "parameter_type"}, {"source": "src_mcp_post_json", "target": "value", "relation": "references", "confidence": "EXTRACTED", "source_file": "src-tauri/src/mcp.rs", "source_location": "L43", "weight": 1.0, "context": "parameter_type"}, {"source": "src_mcp_post_json", "target": "result", "relation": "references", "confidence": "EXTRACTED", "source_file": "src-tauri/src/mcp.rs", "source_location": "L43", "weight": 1.0, "context": "return_type"}, {"source": "src_mcp_post_json", "target": "string", "relation": "references", "confidence": "EXTRACTED", "source_file": "src-tauri/src/mcp.rs", "source_location": "L43", "weight": 1.0, "context": "generic_arg"}, {"source": "users_satnam_workstation_smriti_src_tauri_src_mcp_rs", "target": "src_mcp_wait_for_id", "relation": "contains", "confidence": "EXTRACTED", "source_file": "src-tauri/src/mcp.rs", "source_location": "L54", "weight": 1.0}, {"source": "src_mcp_wait_for_id", "target": "arc", "relation": "references", "confidence": "EXTRACTED", "source_file": "src-tauri/src/mcp.rs", "source_location": "L54", "weight": 1.0, "context": "parameter_type"}, {"source": "src_mcp_wait_for_id", "target": "mutex", "relation": "references", "confidence": "EXTRACTED", "source_file": "src-tauri/src/mcp.rs", "source_location": "L54", "weight": 1.0, "context": "generic_arg"}, {"source": "src_mcp_wait_for_id", "target": "vec", "relation": "references", "confidence": "EXTRACTED", "source_file": "src-tauri/src/mcp.rs", "source_location": "L54", "weight": 1.0, "context": "generic_arg"}, {"source": "src_mcp_wait_for_id", "target": "value", "relation": "references", "confidence": "EXTRACTED", "source_file": "src-tauri/src/mcp.rs", "source_location": "L54", "weight": 1.0, "context": "generic_arg"}, {"source": "src_mcp_wait_for_id", "target": "duration", "relation": "references", "confidence": "EXTRACTED", "source_file": "src-tauri/src/mcp.rs", "source_location": "L54", "weight": 1.0, "context": "parameter_type"}, {"source": "src_mcp_wait_for_id", "target": "result", "relation": "references", "confidence": "EXTRACTED", "source_file": "src-tauri/src/mcp.rs", "source_location": "L54", "weight": 1.0, "context": "return_type"}, {"source": "src_mcp_wait_for_id", "target": "value", "relation": "references", "confidence": "EXTRACTED", "source_file": "src-tauri/src/mcp.rs", "source_location": "L54", "weight": 1.0, "context": "generic_arg"}, {"source": "src_mcp_wait_for_id", "target": "string", "relation": "references", "confidence": "EXTRACTED", "source_file": "src-tauri/src/mcp.rs", "source_location": "L54", "weight": 1.0, "context": "generic_arg"}, {"source": "users_satnam_workstation_smriti_src_tauri_src_mcp_rs", "target": "src_mcp_run_rpc", "relation": "contains", "confidence": "EXTRACTED", "source_file": "src-tauri/src/mcp.rs", "source_location": "L74", "weight": 1.0}, {"source": "src_mcp_run_rpc", "target": "value", "relation": "references", "confidence": "EXTRACTED", "source_file": "src-tauri/src/mcp.rs", "source_location": "L74", "weight": 1.0, "context": "parameter_type"}, {"source": "src_mcp_run_rpc", "target": "result", "relation": "references", "confidence": "EXTRACTED", "source_file": "src-tauri/src/mcp.rs", "source_location": "L74", "weight": 1.0, "context": "return_type"}, {"source": "src_mcp_run_rpc", "target": "value", "relation": "references", "confidence": "EXTRACTED", "source_file": "src-tauri/src/mcp.rs", "source_location": "L74", "weight": 1.0, "context": "generic_arg"}, {"source": "src_mcp_run_rpc", "target": "string", "relation": "references", "confidence": "EXTRACTED", "source_file": "src-tauri/src/mcp.rs", "source_location": "L74", "weight": 1.0, "context": "generic_arg"}, {"source": "users_satnam_workstation_smriti_src_tauri_src_mcp_rs", "target": "src_mcp_list_tools", "relation": "contains", "confidence": "EXTRACTED", "source_file": "src-tauri/src/mcp.rs", "source_location": "L182", "weight": 1.0}, {"source": "src_mcp_list_tools", "target": "result", "relation": "references", "confidence": "EXTRACTED", "source_file": "src-tauri/src/mcp.rs", "source_location": "L182", "weight": 1.0, "context": "return_type"}, {"source": "src_mcp_list_tools", "target": "vec", "relation": "references", "confidence": "EXTRACTED", "source_file": "src-tauri/src/mcp.rs", "source_location": "L182", "weight": 1.0, "context": "generic_arg"}, {"source": "src_mcp_list_tools", "target": "src_mcp_mcptool", "relation": "references", "confidence": "EXTRACTED", "source_file": "src-tauri/src/mcp.rs", "source_location": "L182", "weight": 1.0, "context": "generic_arg"}, {"source": "src_mcp_list_tools", "target": "string", "relation": "references", "confidence": "EXTRACTED", "source_file": "src-tauri/src/mcp.rs", "source_location": "L182", "weight": 1.0, "context": "generic_arg"}, {"source": "users_satnam_workstation_smriti_src_tauri_src_mcp_rs", "target": "src_mcp_call_tool", "relation": "contains", "confidence": "EXTRACTED", "source_file": "src-tauri/src/mcp.rs", "source_location": "L206", "weight": 1.0}, {"source": "src_mcp_call_tool", "target": "value", "relation": "references", "confidence": "EXTRACTED", "source_file": "src-tauri/src/mcp.rs", "source_location": "L206", "weight": 1.0, "context": "parameter_type"}, {"source": "src_mcp_call_tool", "target": "result", "relation": "references", "confidence": "EXTRACTED", "source_file": "src-tauri/src/mcp.rs", "source_location": "L206", "weight": 1.0, "context": "return_type"}, {"source": "src_mcp_call_tool", "target": "string", "relation": "references", "confidence": "EXTRACTED", "source_file": "src-tauri/src/mcp.rs", "source_location": "L206", "weight": 1.0, "context": "generic_arg"}, {"source": "src_mcp_call_tool", "target": "string", "relation": "references", "confidence": "EXTRACTED", "source_file": "src-tauri/src/mcp.rs", "source_location": "L206", "weight": 1.0, "context": "generic_arg"}, {"source": "users_satnam_workstation_smriti_src_tauri_src_mcp_rs", "target": "src_mcp_clean_tool_error", "relation": "contains", "confidence": "EXTRACTED", "source_file": "src-tauri/src/mcp.rs", "source_location": "L236", "weight": 1.0}, {"source": "src_mcp_clean_tool_error", "target": "string", "relation": "references", "confidence": "EXTRACTED", "source_file": "src-tauri/src/mcp.rs", "source_location": "L236", "weight": 1.0, "context": "return_type"}, {"source": "users_satnam_workstation_smriti_src_tauri_src_mcp_rs", "target": "src_mcp_format_tool_text", "relation": "contains", "confidence": "EXTRACTED", "source_file": "src-tauri/src/mcp.rs", "source_location": "L250", "weight": 1.0}, {"source": "src_mcp_format_tool_text", "target": "string", "relation": "references", "confidence": "EXTRACTED", "source_file": "src-tauri/src/mcp.rs", "source_location": "L250", "weight": 1.0, "context": "return_type"}, {"source": "src_mcp_run_rpc", "target": "src_mcp_ingest_sse", "relation": "calls", "context": "call", "confidence": "EXTRACTED", "source_file": "src-tauri/src/mcp.rs", "source_location": "L105", "weight": 1.0}, {"source": "src_mcp_run_rpc", "target": "src_mcp_session_id", "relation": "calls", "context": "call", "confidence": "EXTRACTED", "source_file": "src-tauri/src/mcp.rs", "source_location": "L117", "weight": 1.0}, {"source": "src_mcp_run_rpc", "target": "src_mcp_post_json", "relation": "calls", "context": "call", "confidence": "EXTRACTED", "source_file": "src-tauri/src/mcp.rs", "source_location": "L130", "weight": 1.0}, {"source": "src_mcp_run_rpc", "target": "src_mcp_wait_for_id", "relation": "calls", "context": "call", "confidence": "EXTRACTED", "source_file": "src-tauri/src/mcp.rs", "source_location": "L146", "weight": 1.0}, {"source": "src_mcp_list_tools", "target": "src_mcp_run_rpc", "relation": "calls", "context": "call", "confidence": "EXTRACTED", "source_file": "src-tauri/src/mcp.rs", "source_location": "L184", "weight": 1.0}, {"source": "src_mcp_call_tool", "target": "src_mcp_run_rpc", "relation": "calls", "context": "call", "confidence": "EXTRACTED", "source_file": "src-tauri/src/mcp.rs", "source_location": "L208", "weight": 1.0}, {"source": "src_mcp_call_tool", "target": "src_mcp_clean_tool_error", "relation": "calls", "context": "call", "confidence": "EXTRACTED", "source_file": "src-tauri/src/mcp.rs", "source_location": "L217", "weight": 1.0}, {"source": "src_mcp_call_tool", "target": "src_mcp_format_tool_text", "relation": "calls", "context": "call", "confidence": "EXTRACTED", "source_file": "src-tauri/src/mcp.rs", "source_location": "L230", "weight": 1.0}], "raw_calls": [{"caller_nid": "src_mcp_ingest_sse", "callee": "split", "is_member_call": true, "source_file": "/Users/satnam/Workstation/smriti/src-tauri/src/mcp.rs", "source_location": "L16"}, {"caller_nid": "src_mcp_ingest_sse", "callee": "find", "is_member_call": true, "source_file": "/Users/satnam/Workstation/smriti/src-tauri/src/mcp.rs", "source_location": "L17"}, {"caller_nid": "src_mcp_ingest_sse", "callee": "lines", "is_member_call": true, "source_file": "/Users/satnam/Workstation/smriti/src-tauri/src/mcp.rs", "source_location": "L17"}, {"caller_nid": "src_mcp_ingest_sse", "callee": "starts_with", "is_member_call": true, "source_file": "/Users/satnam/Workstation/smriti/src-tauri/src/mcp.rs", "source_location": "L17"}, {"caller_nid": "src_mcp_ingest_sse", "callee": "trim", "is_member_call": true, "source_file": "/Users/satnam/Workstation/smriti/src-tauri/src/mcp.rs", "source_location": "L20"}, {"caller_nid": "src_mcp_ingest_sse", "callee": "trim_start_matches", "is_member_call": true, "source_file": "/Users/satnam/Workstation/smriti/src-tauri/src/mcp.rs", "source_location": "L20"}, {"caller_nid": "src_mcp_ingest_sse", "callee": "starts_with", "is_member_call": true, "source_file": "/Users/satnam/Workstation/smriti/src-tauri/src/mcp.rs", "source_location": "L21"}, {"caller_nid": "src_mcp_ingest_sse", "callee": "is_some", "is_member_call": true, "source_file": "/Users/satnam/Workstation/smriti/src-tauri/src/mcp.rs", "source_location": "L25"}, {"caller_nid": "src_mcp_ingest_sse", "callee": "is_some", "is_member_call": true, "source_file": "/Users/satnam/Workstation/smriti/src-tauri/src/mcp.rs", "source_location": "L25"}, {"caller_nid": "src_mcp_ingest_sse", "callee": "is_some", "is_member_call": true, "source_file": "/Users/satnam/Workstation/smriti/src-tauri/src/mcp.rs", "source_location": "L25"}, {"caller_nid": "src_mcp_session_id", "callee": "find", "is_member_call": true, "source_file": "/Users/satnam/Workstation/smriti/src-tauri/src/mcp.rs", "source_location": "L35"}, {"caller_nid": "src_mcp_session_id", "callee": "unwrap_or", "is_member_call": true, "source_file": "/Users/satnam/Workstation/smriti/src-tauri/src/mcp.rs", "source_location": "L37"}, {"caller_nid": "src_mcp_session_id", "callee": "find", "is_member_call": true, "source_file": "/Users/satnam/Workstation/smriti/src-tauri/src/mcp.rs", "source_location": "L37"}, {"caller_nid": "src_mcp_session_id", "callee": "is_ascii_hexdigit", "is_member_call": true, "source_file": "/Users/satnam/Workstation/smriti/src-tauri/src/mcp.rs", "source_location": "L38"}, {"caller_nid": "src_mcp_post_json", "callee": "map_err", "is_member_call": true, "source_file": "/Users/satnam/Workstation/smriti/src-tauri/src/mcp.rs", "source_location": "L44"}, {"caller_nid": "src_mcp_post_json", "callee": "json", "is_member_call": true, "source_file": "/Users/satnam/Workstation/smriti/src-tauri/src/mcp.rs", "source_location": "L44"}, {"caller_nid": "src_mcp_post_json", "callee": "header", "is_member_call": true, "source_file": "/Users/satnam/Workstation/smriti/src-tauri/src/mcp.rs", "source_location": "L44"}, {"caller_nid": "src_mcp_post_json", "callee": "post", "is_member_call": true, "source_file": "/Users/satnam/Workstation/smriti/src-tauri/src/mcp.rs", "source_location": "L44"}, {"caller_nid": "src_mcp_wait_for_id", "callee": "find", "is_member_call": true, "source_file": "/Users/satnam/Workstation/smriti/src-tauri/src/mcp.rs", "source_location": "L63"}, {"caller_nid": "src_mcp_run_rpc", "callee": "map_err", "is_member_call": true, "source_file": "/Users/satnam/Workstation/smriti/src-tauri/src/mcp.rs", "source_location": "L75"}, {"caller_nid": "src_mcp_run_rpc", "callee": "timeout", "is_member_call": true, "source_file": "/Users/satnam/Workstation/smriti/src-tauri/src/mcp.rs", "source_location": "L75"}, {"caller_nid": "src_mcp_run_rpc", "callee": "map_err", "is_member_call": true, "source_file": "/Users/satnam/Workstation/smriti/src-tauri/src/mcp.rs", "source_location": "L81"}, {"caller_nid": "src_mcp_run_rpc", "callee": "header", "is_member_call": true, "source_file": "/Users/satnam/Workstation/smriti/src-tauri/src/mcp.rs", "source_location": "L81"}, {"caller_nid": "src_mcp_run_rpc", "callee": "is_success", "is_member_call": true, "source_file": "/Users/satnam/Workstation/smriti/src-tauri/src/mcp.rs", "source_location": "L88"}, {"caller_nid": "src_mcp_run_rpc", "callee": "status", "is_member_call": true, "source_file": "/Users/satnam/Workstation/smriti/src-tauri/src/mcp.rs", "source_location": "L88"}, {"caller_nid": "src_mcp_run_rpc", "callee": "bytes_stream", "is_member_call": true, "source_file": "/Users/satnam/Workstation/smriti/src-tauri/src/mcp.rs", "source_location": "L92"}, {"caller_nid": "src_mcp_run_rpc", "callee": "push_str", "is_member_call": true, "source_file": "/Users/satnam/Workstation/smriti/src-tauri/src/mcp.rs", "source_location": "L103"}, {"caller_nid": "src_mcp_run_rpc", "callee": "abort", "is_member_call": true, "source_file": "/Users/satnam/Workstation/smriti/src-tauri/src/mcp.rs", "source_location": "L123"}, {"caller_nid": "src_mcp_run_rpc", "callee": "abort", "is_member_call": true, "source_file": "/Users/satnam/Workstation/smriti/src-tauri/src/mcp.rs", "source_location": "L178"}, {"caller_nid": "src_mcp_list_tools", "callee": "trim_end_matches", "is_member_call": true, "source_file": "/Users/satnam/Workstation/smriti/src-tauri/src/mcp.rs", "source_location": "L183"}, {"caller_nid": "src_mcp_list_tools", "callee": "unwrap_or_default", "is_member_call": true, "source_file": "/Users/satnam/Workstation/smriti/src-tauri/src/mcp.rs", "source_location": "L186"}, {"caller_nid": "src_mcp_list_tools", "callee": "cloned", "is_member_call": true, "source_file": "/Users/satnam/Workstation/smriti/src-tauri/src/mcp.rs", "source_location": "L186"}, {"caller_nid": "src_mcp_list_tools", "callee": "and_then", "is_member_call": true, "source_file": "/Users/satnam/Workstation/smriti/src-tauri/src/mcp.rs", "source_location": "L186"}, {"caller_nid": "src_mcp_list_tools", "callee": "pointer", "is_member_call": true, "source_file": "/Users/satnam/Workstation/smriti/src-tauri/src/mcp.rs", "source_location": "L186"}, {"caller_nid": "src_mcp_list_tools", "callee": "as_array", "is_member_call": true, "source_file": "/Users/satnam/Workstation/smriti/src-tauri/src/mcp.rs", "source_location": "L188"}, {"caller_nid": "src_mcp_list_tools", "callee": "filter_map", "is_member_call": true, "source_file": "/Users/satnam/Workstation/smriti/src-tauri/src/mcp.rs", "source_location": "L192"}, {"caller_nid": "src_mcp_list_tools", "callee": "into_iter", "is_member_call": true, "source_file": "/Users/satnam/Workstation/smriti/src-tauri/src/mcp.rs", "source_location": "L192"}, {"caller_nid": "src_mcp_list_tools", "callee": "as_str", "is_member_call": true, "source_file": "/Users/satnam/Workstation/smriti/src-tauri/src/mcp.rs", "source_location": "L196"}, {"caller_nid": "src_mcp_list_tools", "callee": "and_then", "is_member_call": true, "source_file": "/Users/satnam/Workstation/smriti/src-tauri/src/mcp.rs", "source_location": "L197"}, {"caller_nid": "src_mcp_list_tools", "callee": "as_str", "is_member_call": true, "source_file": "/Users/satnam/Workstation/smriti/src-tauri/src/mcp.rs", "source_location": "L199"}, {"caller_nid": "src_mcp_call_tool", "callee": "trim_end_matches", "is_member_call": true, "source_file": "/Users/satnam/Workstation/smriti/src-tauri/src/mcp.rs", "source_location": "L207"}, {"caller_nid": "src_mcp_call_tool", "callee": "and_then", "is_member_call": true, "source_file": "/Users/satnam/Workstation/smriti/src-tauri/src/mcp.rs", "source_location": "L216"}, {"caller_nid": "src_mcp_call_tool", "callee": "and_then", "is_member_call": true, "source_file": "/Users/satnam/Workstation/smriti/src-tauri/src/mcp.rs", "source_location": "L216"}, {"caller_nid": "src_mcp_call_tool", "callee": "as_str", "is_member_call": true, "source_file": "/Users/satnam/Workstation/smriti/src-tauri/src/mcp.rs", "source_location": "L216"}, {"caller_nid": "src_mcp_call_tool", "callee": "ok_or", "is_member_call": true, "source_file": "/Users/satnam/Workstation/smriti/src-tauri/src/mcp.rs", "source_location": "L220"}, {"caller_nid": "src_mcp_call_tool", "callee": "and_then", "is_member_call": true, "source_file": "/Users/satnam/Workstation/smriti/src-tauri/src/mcp.rs", "source_location": "L221"}, {"caller_nid": "src_mcp_call_tool", "callee": "as_bool", "is_member_call": true, "source_file": "/Users/satnam/Workstation/smriti/src-tauri/src/mcp.rs", "source_location": "L221"}, {"caller_nid": "src_mcp_call_tool", "callee": "unwrap_or", "is_member_call": true, "source_file": "/Users/satnam/Workstation/smriti/src-tauri/src/mcp.rs", "source_location": "L222"}, {"caller_nid": "src_mcp_call_tool", "callee": "and_then", "is_member_call": true, "source_file": "/Users/satnam/Workstation/smriti/src-tauri/src/mcp.rs", "source_location": "L222"}, {"caller_nid": "src_mcp_call_tool", "callee": "pointer", "is_member_call": true, "source_file": "/Users/satnam/Workstation/smriti/src-tauri/src/mcp.rs", "source_location": "L222"}, {"caller_nid": "src_mcp_call_tool", "callee": "as_str", "is_member_call": true, "source_file": "/Users/satnam/Workstation/smriti/src-tauri/src/mcp.rs", "source_location": "L224"}, {"caller_nid": "src_mcp_call_tool", "callee": "and_then", "is_member_call": true, "source_file": "/Users/satnam/Workstation/smriti/src-tauri/src/mcp.rs", "source_location": "L229"}, {"caller_nid": "src_mcp_call_tool", "callee": "pointer", "is_member_call": true, "source_file": "/Users/satnam/Workstation/smriti/src-tauri/src/mcp.rs", "source_location": "L229"}, {"caller_nid": "src_mcp_call_tool", "callee": "as_str", "is_member_call": true, "source_file": "/Users/satnam/Workstation/smriti/src-tauri/src/mcp.rs", "source_location": "L229"}, {"caller_nid": "src_mcp_clean_tool_error", "callee": "trim", "is_member_call": true, "source_file": "/Users/satnam/Workstation/smriti/src-tauri/src/mcp.rs", "source_location": "L237"}, {"caller_nid": "src_mcp_clean_tool_error", "callee": "strip_prefix", "is_member_call": true, "source_file": "/Users/satnam/Workstation/smriti/src-tauri/src/mcp.rs", "source_location": "L238"}, {"caller_nid": "src_mcp_clean_tool_error", "callee": "find", "is_member_call": true, "source_file": "/Users/satnam/Workstation/smriti/src-tauri/src/mcp.rs", "source_location": "L239"}, {"caller_nid": "src_mcp_clean_tool_error", "callee": "trim", "is_member_call": true, "source_file": "/Users/satnam/Workstation/smriti/src-tauri/src/mcp.rs", "source_location": "L240"}, {"caller_nid": "src_mcp_clean_tool_error", "callee": "trim", "is_member_call": true, "source_file": "/Users/satnam/Workstation/smriti/src-tauri/src/mcp.rs", "source_location": "L243"}, {"caller_nid": "src_mcp_clean_tool_error", "callee": "unwrap_or", "is_member_call": true, "source_file": "/Users/satnam/Workstation/smriti/src-tauri/src/mcp.rs", "source_location": "L243"}, {"caller_nid": "src_mcp_clean_tool_error", "callee": "strip_prefix", "is_member_call": true, "source_file": "/Users/satnam/Workstation/smriti/src-tauri/src/mcp.rs", "source_location": "L243"}, {"caller_nid": "src_mcp_format_tool_text", "callee": "trim", "is_member_call": true, "source_file": "/Users/satnam/Workstation/smriti/src-tauri/src/mcp.rs", "source_location": "L251"}]}